cnholidays/__init__.py
cnholidays/core.py
cnholidays/examples.py
cnholidays-0.1.0.dist-info/licenses/LICENSE
cnholidays-0.1.0.dist-info/METADATA
cnholidays-0.1.0.dist-info/WHEEL
cnholidays-0.1.0.dist-info/top_level.txt
cnholidays-0.1.0.dist-info/RECORD
