Metadata-Version: 2.4
Name: cnholidays
Version: 0.1.0
Summary: A tool to get Chinese holidays and workdays
Home-page: https://github.com/yourusername/cnholidays
Author: Python Developer
Author-email: Henry Wang <whlweb@gmail.com>
Project-URL: Homepage, https://github.com/whlweb/cnholidays
Classifier: Programming Language :: Python :: 3
Classifier: License :: OSI Approved :: MIT License
Classifier: Operating System :: OS Independent
Requires-Python: >=3.6
License-File: LICENSE
Dynamic: author
Dynamic: home-page
Dynamic: license-file
Dynamic: requires-python
